env_color_logger/__init__.py
env_color_logger/color.py
env_color_logger-0.0.3.dist-info/LICENSE
env_color_logger-0.0.3.dist-info/METADATA
env_color_logger-0.0.3.dist-info/WHEEL
env_color_logger-0.0.3.dist-info/top_level.txt
env_color_logger-0.0.3.dist-info/RECORD
